charli3_dendrite/__init__.py
charli3_dendrite/backend/__init__.py
charli3_dendrite/backend/backend_base.py
charli3_dendrite/backend/blockfrost/__init__.py
charli3_dendrite/backend/blockfrost/models.py
charli3_dendrite/backend/dbsync/__init__.py
charli3_dendrite/backend/dbsync/models.py
charli3_dendrite/backend/ogmios_kupo/__init__.py
charli3_dendrite/backend/ogmios_kupo/models.py
charli3_dendrite/backend/utils.py
charli3_dendrite/dataclasses/__init__.py
charli3_dendrite/dataclasses/datums.py
charli3_dendrite/dataclasses/models.py
charli3_dendrite/dexs/__init__.py
charli3_dendrite/dexs/amm/__init__.py
charli3_dendrite/dexs/amm/amm_base.py
charli3_dendrite/dexs/amm/amm_types.py
charli3_dendrite/dexs/amm/cswap.py
charli3_dendrite/dexs/amm/minswap.py
charli3_dendrite/dexs/amm/muesli.py
charli3_dendrite/dexs/amm/spectrum.py
charli3_dendrite/dexs/amm/splash.py
charli3_dendrite/dexs/amm/sundae.py
charli3_dendrite/dexs/amm/vyfi.py
charli3_dendrite/dexs/amm/wingriders.py
charli3_dendrite/dexs/core/__init__.py
charli3_dendrite/dexs/core/base.py
charli3_dendrite/dexs/core/errors.py
charli3_dendrite/dexs/ob/__init__.py
charli3_dendrite/dexs/ob/axo.py
charli3_dendrite/dexs/ob/djed.py
charli3_dendrite/dexs/ob/geniusyield.py
charli3_dendrite/dexs/ob/ob_base.py
charli3_dendrite/utility.py
charli3_dendrite-1.4.3.dist-info/METADATA
charli3_dendrite-1.4.3.dist-info/WHEEL
charli3_dendrite-1.4.3.dist-info/licenses/LICENSE
charli3_dendrite-1.4.3.dist-info/RECORD
