Metadata-Version: 2.4
Name: charli3_dendrite
Version: 1.4.3
Summary: 
License-File: LICENSE
Author: Elder Millenial
Author-email: eldermillenial@protonmail.com
Requires-Python: >=3.10,<4.0
Classifier: Programming Language :: Python :: 3
Classifier: Programming Language :: Python :: 3.10
Classifier: Programming Language :: Python :: 3.11
Classifier: Programming Language :: Python :: 3.12
Classifier: Programming Language :: Python :: 3.13
Classifier: Programming Language :: Python :: 3.14
Requires-Dist: blockfrost-python (>=0.6.0,<0.7.0)
Requires-Dist: bump-my-version (>=1.1.4,<2.0.0)
Requires-Dist: psycopg[binary,pool] (>=3.1.13,<4.0.0)
Requires-Dist: pycardano (==0.18.0)
Requires-Dist: pydantic (>=2.5.2,<3.0.0)
Requires-Dist: python-dotenv (==1.0.1)
Requires-Dist: requests (>=2.31.0,<3.0.0)
